deadlineapi/Contact.py
deadlineapi/DeadlineObject.py
deadlineapi/DirectoryItem.py
deadlineapi/Endpoint.py
deadlineapi/Loader.py
deadlineapi/Location.py
deadlineapi/Validation.py
deadlineapi/Version.py
deadlineapi/__init__.py
deadlineapi/__main__.py
pyDeadlineAPI-0.0.0.dist-info/METADATA
pyDeadlineAPI-0.0.0.dist-info/WHEEL
pyDeadlineAPI-0.0.0.dist-info/entry_points.txt
pyDeadlineAPI-0.0.0.dist-info/top_level.txt
pyDeadlineAPI-0.0.0.dist-info/RECORD
