Metadata-Version: 2.1
Name: pyDeadlineAPI
Version: 0.0.0
Summary: Access DeadlineAPI directories or endpoint directly
Home-page: https://github.com/DeadlineAPI/pyDeadlineAPI
Author: Maximilian Noppel
Author-email: max@noppelmax.online
License: MIT
Platform: UNKNOWN
Classifier: License :: OSI Approved :: MIT License
Classifier: Programming Language :: Python :: 3
Classifier: Programming Language :: Python :: 3.7
Requires-Dist: jsonschema (==3.0.1)
Requires-Dist: requests (==2.21.0)
